<?xml version="1.0" encoding="utf-8"?>
<edmx:Edmx Version="1.0" xmlns:edmx="http://schemas.microsoft.com/ado/2007/06/edmx" xmlns:m="http://schemas.microsoft.com/ado/2007/08/dataservices/metadata" xmlns:sap="http://www.sap.com/Protocols/SAPData">
    <edmx:DataServices m:DataServiceVersion="2.0">
        <Schema Namespace="ZFIORI_EGITIM_SRV" xml:lang="tr" sap:schema-version="1" xmlns="http://schemas.microsoft.com/ado/2008/09/edm">
            <EntityType Name="EUrunler" sap:content-version="1">
                <Key>
                    <PropertyRef Name="Atwrt"/>
                </Key>
                <Property Name="Atwrt" Type="Edm.String" Nullable="false" MaxLength="30" sap:label="Krkt.değeri" sap:creatable="false" sap:updatable="false" sap:sortable="false" sap:filterable="false"/>
                <Property Name="Zkas" Type="Edm.String" Nullable="false" MaxLength="1" sap:label="Kassbohrer web sayfa" sap:creatable="false" sap:updatable="false" sap:sortable="false" sap:filterable="false"/>
                <Property Name="Ztls" Type="Edm.String" Nullable="false" MaxLength="1" sap:label="Talson web sayfası" sap:creatable="false" sap:updatable="false" sap:sortable="false" sap:filterable="false"/>
                <Property Name="Ztir" Type="Edm.String" Nullable="false" MaxLength="1" sap:label="Tırsan web sayfası" sap:creatable="false" sap:updatable="false" sap:sortable="false" sap:filterable="false"/>
            </EntityType>
            <EntityType Name="EKarakteristik" sap:content-version="1">
                <Key>
                    <PropertyRef Name="Atwrt"/>
                </Key>
                <Property Name="Atwrt" Type="Edm.String" Nullable="false" MaxLength="30" sap:label="Krkt.değeri" sap:creatable="false" sap:updatable="false" sap:sortable="false" sap:filterable="false"/>
                <Property Name="NameChar" Type="Edm.String" Nullable="false" MaxLength="30" sap:label="Karakteristik" sap:creatable="false" sap:updatable="false" sap:sortable="false" sap:filterable="false"/>
                <Property Name="DescrChar" Type="Edm.String" Nullable="false" MaxLength="30" sap:label="Tanım" sap:creatable="false" sap:updatable="false" sap:sortable="false" sap:filterable="false"/>
                <Property Name="Zsecim" Type="Edm.String" Nullable="false" MaxLength="1" sap:label="Gösterge: Karakteristik devralındı" sap:creatable="false" sap:updatable="false" sap:sortable="false" sap:filterable="false"/>
                <Property Name="Zkars" Type="Edm.String" Nullable="false" MaxLength="3" sap:label="Grup Sıra No" sap:creatable="false" sap:updatable="false" sap:sortable="false" sap:filterable="false"/>
                <Property Name="Zkarg" Type="Edm.String" Nullable="false" MaxLength="30" sap:label="Grup Adı" sap:creatable="false" sap:updatable="false" sap:sortable="false" sap:filterable="false"/>
                <Property Name="Loekz" Type="Edm.String" Nullable="false" sap:label="Silme göstergesi" sap:creatable="false" sap:updatable="false" sap:sortable="false" sap:filterable="false"/>
                <Property Name="Zicrs" Type="Edm.String" Nullable="false" MaxLength="3" sap:label="Kar.Sıra" sap:creatable="false" sap:updatable="false" sap:sortable="false" sap:filterable="false"/>
                <Property Name="StdOps" Type="Edm.String" Nullable="false" sap:label="Silme göstergesi" sap:creatable="false" sap:updatable="false" sap:sortable="false" sap:filterable="false"/>
                <Property Name="CharValue" Type="Edm.String" Nullable="false" MaxLength="30" sap:label="Krkt.değeri" sap:creatable="false" sap:updatable="false" sap:sortable="false" sap:filterable="false"/>
                <Property Name="DescrCval" Type="Edm.String" Nullable="false" MaxLength="30" sap:label="Tanım" sap:creatable="false" sap:updatable="false" sap:sortable="false" sap:filterable="false"/>
                <Property Name="Metin" Type="Edm.String" Nullable="false" sap:label="Metin" sap:creatable="false" sap:updatable="false" sap:sortable="false" sap:filterable="false"/>
                <Property Name="MetinEz" Type="Edm.String" Nullable="false" sap:label="Metin" sap:creatable="false" sap:updatable="false" sap:sortable="false" sap:filterable="false"/>
                <Property Name="ISpras" Type="Edm.String" Nullable="false" MaxLength="2" sap:label="Dİl" sap:creatable="false" sap:updatable="false" sap:sortable="false" sap:filterable="false"/>
            </EntityType>
            <EntityType Name="MalzFiyat" sap:content-version="1">
                <Key>
                    <PropertyRef Name="Matnr"/>
                </Key>
                <Property Name="Matnr" Type="Edm.String" Nullable="false" MaxLength="18" sap:label="Malzeme" sap:creatable="false" sap:updatable="false" sap:sortable="false" sap:filterable="false"/>
                <Property Name="Maktx" Type="Edm.String" Nullable="false" MaxLength="40" sap:label="Tanım" sap:creatable="false" sap:updatable="false" sap:sortable="false" sap:filterable="false"/>
                <Property Name="Uretici" Type="Edm.String" Nullable="false" MaxLength="10" sap:label="Üretici" sap:creatable="false" sap:updatable="false" sap:sortable="false" sap:filterable="false"/>
                <Property Name="Ureticiadi" Type="Edm.String" Nullable="false" MaxLength="30" sap:label="Ad 1" sap:creatable="false" sap:updatable="false" sap:sortable="false" sap:filterable="false"/>
                <Property Name="Fiyat1" Type="Edm.Decimal" Nullable="false" Precision="14" Scale="3" sap:unit="Dvz1" sap:label="Tutar" sap:creatable="false" sap:updatable="false" sap:sortable="false" sap:filterable="false"/>
                <Property Name="Dvz1" Type="Edm.String" Nullable="false" MaxLength="5" sap:label="Para birimi" sap:creatable="false" sap:updatable="false" sap:sortable="false" sap:filterable="false" sap:semantics="currency-code"/>
                <Property Name="FiyatBoleni1" Type="Edm.Decimal" Nullable="false" Precision="8" Scale="3" sap:label="Fiyat birimi" sap:creatable="false" sap:updatable="false" sap:sortable="false" sap:filterable="false"/>
                <Property Name="FiyatBirimi1" Type="Edm.String" Nullable="false" MaxLength="3" sap:label="Ölçü birimi" sap:creatable="false" sap:updatable="false" sap:sortable="false" sap:filterable="false" sap:semantics="unit-of-measure"/>
                <Property Name="Meins" Type="Edm.String" Nullable="false" MaxLength="3" sap:label="Temel ölçü brm." sap:creatable="false" sap:updatable="false" sap:sortable="false" sap:filterable="false" sap:semantics="unit-of-measure"/>
                <Property Name="Kosul" Type="Edm.String" Nullable="false" MaxLength="50" sap:label="Açıklama" sap:creatable="false" sap:updatable="false" sap:sortable="false" sap:filterable="false"/>
                <Property Name="Kdvorn" Type="Edm.Decimal" Nullable="false" Precision="14" Scale="3" sap:label="KDV Oranı" sap:creatable="false" sap:updatable="false" sap:sortable="false" sap:filterable="false"/>
                <Property Name="Urngrp1" Type="Edm.String" Nullable="false" MaxLength="9" sap:label="Mal grubu" sap:creatable="false" sap:updatable="false" sap:sortable="false" sap:filterable="false"/>
                <Property Name="Urngrpad1" Type="Edm.String" Nullable="false" MaxLength="20" sap:label="Mal grp.tanımı" sap:creatable="false" sap:updatable="false" sap:sortable="false" sap:filterable="false"/>
                <Property Name="Urngrp2" Type="Edm.String" Nullable="false" MaxLength="18" sap:label="Harici mal gr." sap:creatable="false" sap:updatable="false" sap:sortable="false" sap:filterable="false"/>
                <Property Name="Urngrpad2" Type="Edm.String" Nullable="false" MaxLength="20" sap:label="Hrc.mal grp.tnm" sap:creatable="false" sap:updatable="false" sap:sortable="false" sap:filterable="false"/>
                <Property Name="Urngrp3" Type="Edm.String" Nullable="false" MaxLength="8" sap:label="Navlun grubu" sap:creatable="false" sap:updatable="false" sap:sortable="false" sap:filterable="false"/>
                <Property Name="Urngrpad3" Type="Edm.String" Nullable="false" MaxLength="20" sap:label="Tanım" sap:creatable="false" sap:updatable="false" sap:sortable="false" sap:filterable="false"/>
                <Property Name="MinsipAdedi" Type="Edm.Decimal" Nullable="false" Precision="13" Scale="3" sap:unit="Meins" sap:label="Miktar" sap:creatable="false" sap:updatable="false" sap:sortable="false" sap:filterable="false"/>
                <Property Name="EkAlan1" Type="Edm.String" Nullable="false" MaxLength="255" sap:label="Char255" sap:creatable="false" sap:updatable="false" sap:sortable="false" sap:filterable="false"/>
                <Property Name="EkAlan2" Type="Edm.String" Nullable="false" MaxLength="255" sap:label="Char255" sap:creatable="false" sap:updatable="false" sap:sortable="false" sap:filterable="false"/>
                <Property Name="EkAlan3" Type="Edm.String" Nullable="false" MaxLength="255" sap:label="Char255" sap:creatable="false" sap:updatable="false" sap:sortable="false" sap:filterable="false"/>
                <Property Name="EkAlan4" Type="Edm.String" Nullable="false" MaxLength="255" sap:label="Char255" sap:creatable="false" sap:updatable="false" sap:sortable="false" sap:filterable="false"/>
                <Property Name="Zb2b" Type="Edm.String" Nullable="false" MaxLength="1" sap:label="B2B ye gönderilecek" sap:creatable="false" sap:updatable="false" sap:sortable="false" sap:filterable="false"/>
            </EntityType>
            <EntityType Name="Fiyat" sap:content-version="1">
                <Key>
                    <PropertyRef Name="Matnr"/>
                </Key>
                <Property Name="Kappl" Type="Edm.String" Nullable="false" MaxLength="2" sap:label="Uygulama" sap:creatable="false" sap:updatable="false" sap:sortable="false" sap:filterable="false"/>
                <Property Name="Kschl" Type="Edm.String" Nullable="false" MaxLength="4" sap:label="Koşul türü" sap:creatable="false" sap:updatable="false" sap:sortable="false" sap:filterable="false"/>
                <Property Name="Pltyp" Type="Edm.String" Nullable="false" MaxLength="2" sap:label="Fiyat listesi" sap:creatable="false" sap:updatable="false" sap:sortable="false" sap:filterable="false"/>
                <Property Name="Matnr" Type="Edm.String" Nullable="false" MaxLength="18" sap:label="Malzeme" sap:creatable="false" sap:updatable="false" sap:sortable="false" sap:filterable="false"/>
                <Property Name="Kbetr" Type="Edm.Decimal" Nullable="false" Precision="12" Scale="3" sap:unit="Konwa" sap:label="Tutar" sap:creatable="false" sap:updatable="false" sap:sortable="false" sap:filterable="false"/>
                <Property Name="Konwa" Type="Edm.String" Nullable="false" MaxLength="5" sap:label="Koşul para brm." sap:creatable="false" sap:updatable="false" sap:sortable="false" sap:filterable="false" sap:semantics="currency-code"/>
                <Property Name="Kpein" Type="Edm.Decimal" Nullable="false" Precision="8" Scale="3" sap:label="Fiyat birimi" sap:creatable="false" sap:updatable="false" sap:sortable="false" sap:filterable="false"/>
                <Property Name="Kmein" Type="Edm.String" Nullable="false" MaxLength="3" sap:label="Ölçü birimi" sap:creatable="false" sap:updatable="false" sap:sortable="false" sap:filterable="false" sap:semantics="unit-of-measure"/>
            </EntityType>
            <EntityType Name="KayitDeneme" sap:content-version="1">
                <Key>
                    <PropertyRef Name="Matnr"/>
                </Key>
                <Property Name="OlusTarih" Type="Edm.DateTime" Nullable="false" Precision="0" sap:label="Zaman damgası" sap:creatable="false" sap:updatable="false" sap:sortable="false" sap:filterable="false"/>
                <Property Name="Silme" Type="Edm.Boolean" Nullable="false" sap:label="Gösterge" sap:creatable="false" sap:updatable="false" sap:sortable="false" sap:filterable="false"/>
                <Property Name="Miktar" Type="Edm.String" Nullable="false" MaxLength="20" sap:creatable="false" sap:updatable="false" sap:sortable="false" sap:filterable="false"/>
                <Property Name="Matnr" Type="Edm.String" Nullable="false" MaxLength="35" sap:creatable="false" sap:updatable="false" sap:sortable="false" sap:filterable="false"/>
            </EntityType>
            <EntityType Name="Vendor" sap:content-version="1">
                <Key>
                    <PropertyRef Name="Lifnr"/>
                </Key>
                <Property Name="Lifnr" Type="Edm.String" Nullable="false" MaxLength="10" sap:label="Satıcı" sap:creatable="false" sap:updatable="false" sap:sortable="false" sap:filterable="false"/>
                <Property Name="Name1" Type="Edm.String" Nullable="false" MaxLength="35" sap:label="Ad" sap:creatable="false" sap:updatable="false" sap:sortable="false" sap:filterable="false"/>
            </EntityType>
            <EntityType Name="Sirket" sap:content-version="1">
                <Key>
                    <PropertyRef Name="Bukrs"/>
                </Key>
                <Property Name="Bukrs" Type="Edm.String" Nullable="false" MaxLength="4" sap:label="Şirket kodu" sap:creatable="false" sap:updatable="false" sap:sortable="false" sap:filterable="false"/>
                <Property Name="Butxt" Type="Edm.String" Nullable="false" MaxLength="25" sap:label="Şirket adı" sap:creatable="false" sap:updatable="false" sap:sortable="false" sap:filterable="false"/>
            </EntityType>
            <EntityType Name="Mip" sap:content-version="1">
                <Key>
                    <PropertyRef Name="Werks"/>
                    <PropertyRef Name="Dispo"/>
                </Key>
                <Property Name="Werks" Type="Edm.String" Nullable="false" MaxLength="4" sap:label="Üretim yeri" sap:creatable="false" sap:updatable="false" sap:sortable="false" sap:filterable="false"/>
                <Property Name="Dispo" Type="Edm.String" Nullable="false" MaxLength="3" sap:label="MİP sorumlusu" sap:creatable="false" sap:updatable="false" sap:sortable="false" sap:filterable="false"/>
                <Property Name="Dsnam" Type="Edm.String" Nullable="false" MaxLength="18" sap:label="MİP sorumlusu" sap:creatable="false" sap:updatable="false" sap:sortable="false" sap:filterable="false"/>
            </EntityType>
            <EntityType Name="Musteri" sap:content-version="1">
                <Key>
                    <PropertyRef Name="Kunnr"/>
                </Key>
                <Property Name="Kunnr" Type="Edm.String" Nullable="false" MaxLength="10" sap:label="Müşteri" sap:creatable="false" sap:updatable="false" sap:sortable="false" sap:filterable="false"/>
                <Property Name="Name1" Type="Edm.String" Nullable="false" MaxLength="35" sap:label="Ad" sap:creatable="false" sap:updatable="false" sap:sortable="false" sap:filterable="false"/>
            </EntityType>
            <EntityType Name="NakitList" sap:content-version="1">
                <Key>
                    <PropertyRef Name="Belnr"/>
                </Key>
                <Property Name="Belnr" Type="Edm.String" Nullable="false" MaxLength="10" sap:label="Belge numarası" sap:creatable="false" sap:updatable="false" sap:sortable="false" sap:filterable="false"/>
                <Property Name="Mblnr" Type="Edm.String" Nullable="false" MaxLength="10" sap:label="Malzeme belgesi" sap:creatable="false" sap:updatable="false" sap:sortable="false" sap:filterable="false"/>
                <Property Name="Budat" Type="Edm.DateTime" Precision="7" sap:label="Kayıt tarihi" sap:creatable="false" sap:updatable="false" sap:sortable="false" sap:filterable="false"/>
                <Property Name="Bukrs" Type="Edm.String" Nullable="false" MaxLength="4" sap:label="Şirket kodu" sap:creatable="false" sap:updatable="false" sap:sortable="false" sap:filterable="false"/>
                <Property Name="Dispo" Type="Edm.String" Nullable="false" MaxLength="3" sap:label="MİP sorumlusu" sap:creatable="false" sap:updatable="false" sap:sortable="false" sap:filterable="false"/>
                <Property Name="Lifnr" Type="Edm.String" Nullable="false" MaxLength="10" sap:label="Satıcı" sap:creatable="false" sap:updatable="false" sap:sortable="false" sap:filterable="false"/>
                <Property Name="Lname" Type="Edm.String" Nullable="false" MaxLength="15" sap:label="Export File Name" sap:creatable="false" sap:updatable="false" sap:sortable="false" sap:filterable="false"/>
                <Property Name="Ebeln" Type="Edm.String" Nullable="false" MaxLength="10" sap:label="Satınalma blg" sap:creatable="false" sap:updatable="false" sap:sortable="false" sap:filterable="false"/>
                <Property Name="Ekgrp" Type="Edm.String" Nullable="false" MaxLength="3" sap:label="Satınalma grubu" sap:creatable="false" sap:updatable="false" sap:sortable="false" sap:filterable="false"/>
                <Property Name="EkgrpMnl" Type="Edm.String" Nullable="false" MaxLength="3" sap:label="Satınalma grubu" sap:creatable="false" sap:updatable="false" sap:sortable="false" sap:filterable="false"/>
                <Property Name="Xblnr" Type="Edm.String" Nullable="false" MaxLength="16" sap:label="Referans" sap:creatable="false" sap:updatable="false" sap:sortable="false" sap:filterable="false"/>
                <Property Name="Fkdat" Type="Edm.DateTime" Precision="7" sap:label="Ftrl.tarihi" sap:creatable="false" sap:updatable="false" sap:sortable="false" sap:filterable="false"/>
                <Property Name="Wrbtr" Type="Edm.Decimal" Nullable="false" Precision="14" Scale="3" sap:unit="Waers" sap:label="Tutar" sap:creatable="false" sap:updatable="false" sap:sortable="false" sap:filterable="false"/>
                <Property Name="Waers" Type="Edm.String" Nullable="false" MaxLength="5" sap:label="Para birimi" sap:creatable="false" sap:updatable="false" sap:sortable="false" sap:filterable="false" sap:semantics="currency-code"/>
                <Property Name="Descr" Type="Edm.String" Nullable="false" MaxLength="50" sap:label="Açıklama" sap:creatable="false" sap:updatable="false" sap:sortable="false" sap:filterable="false"/>
                <Property Name="Uname" Type="Edm.String" Nullable="false" MaxLength="12" sap:label="Kullanıcı adı" sap:creatable="false" sap:updatable="false" sap:sortable="false" sap:filterable="false"/>
                <Property Name="Cpudt" Type="Edm.DateTime" Precision="7" sap:label="Giriş tarihi" sap:creatable="false" sap:updatable="false" sap:sortable="false" sap:filterable="false"/>
                <Property Name="Cputm" Type="Edm.Time" Precision="0" sap:label="Giriş saati" sap:creatable="false" sap:updatable="false" sap:sortable="false" sap:filterable="false"/>
                <Property Name="Oonay" Type="Edm.String" Nullable="false" MaxLength="1" sap:label="Sonuc" sap:creatable="false" sap:updatable="false" sap:sortable="false" sap:filterable="false"/>
                <Property Name="Ouname" Type="Edm.String" Nullable="false" MaxLength="12" sap:label="Onaylayan" sap:creatable="false" sap:updatable="false" sap:sortable="false" sap:filterable="false"/>
                <Property Name="Ocpudt" Type="Edm.DateTime" Precision="7" sap:label="OnayTarihi" sap:creatable="false" sap:updatable="false" sap:sortable="false" sap:filterable="false"/>
                <Property Name="Ocputm" Type="Edm.Time" Precision="0" sap:label="Onay Saati" sap:creatable="false" sap:updatable="false" sap:sortable="false" sap:filterable="false"/>
            </EntityType>
            <EntityType Name="EDepo" sap:content-version="1">
                <Key>
                    <PropertyRef Name="Lgnum"/>
                    <PropertyRef Name="Lqnum"/>
                </Key>
                <Property Name="Lgnum" Type="Edm.String" Nullable="false" MaxLength="3" sap:label="Depo numarası" sap:creatable="false" sap:updatable="false" sap:sortable="false" sap:filterable="false"/>
                <Property Name="Lqnum" Type="Edm.String" Nullable="false" MaxLength="10" sap:label="Adr.stoku" sap:creatable="false" sap:updatable="false" sap:sortable="false" sap:filterable="false"/>
                <Property Name="Matnr" Type="Edm.String" Nullable="false" MaxLength="18" sap:label="Malzeme" sap:creatable="false" sap:updatable="false" sap:sortable="false" sap:filterable="false"/>
                <Property Name="Werks" Type="Edm.String" Nullable="false" MaxLength="4" sap:label="Üretim yeri" sap:creatable="false" sap:updatable="false" sap:sortable="false" sap:filterable="false"/>
                <Property Name="Charg" Type="Edm.String" Nullable="false" MaxLength="10" sap:label="Parti" sap:creatable="false" sap:updatable="false" sap:sortable="false" sap:filterable="false"/>
                <Property Name="Bestq" Type="Edm.String" Nullable="false" MaxLength="1" sap:label="Stok niteliği" sap:creatable="false" sap:updatable="false" sap:sortable="false" sap:filterable="false"/>
                <Property Name="Sobkz" Type="Edm.String" Nullable="false" MaxLength="1" sap:label="Özel stok" sap:creatable="false" sap:updatable="false" sap:sortable="false" sap:filterable="false"/>
                <Property Name="Sonum" Type="Edm.String" Nullable="false" MaxLength="16" sap:label="Özel stok no." sap:creatable="false" sap:updatable="false" sap:sortable="false" sap:filterable="false"/>
                <Property Name="Lgtyp" Type="Edm.String" Nullable="false" MaxLength="3" sap:label="Depo tipi" sap:creatable="false" sap:updatable="false" sap:sortable="false" sap:filterable="false"/>
                <Property Name="Lgpla" Type="Edm.String" Nullable="false" MaxLength="10" sap:label="Depo adresi" sap:creatable="false" sap:updatable="false" sap:sortable="false" sap:filterable="false"/>
                <Property Name="Gesme" Type="Edm.Decimal" Nullable="false" Precision="13" Scale="3" sap:label="Toplam stok" sap:creatable="false" sap:updatable="false" sap:sortable="false" sap:filterable="false"/>
                <Property Name="Lgort" Type="Edm.String" Nullable="false" MaxLength="4" sap:label="Depo yeri" sap:creatable="false" sap:updatable="false" sap:sortable="false" sap:filterable="false"/>
                <Property Name="Meins" Type="Edm.String" Nullable="false" MaxLength="3" sap:label="Temel ölçü brm." sap:creatable="false" sap:updatable="false" sap:sortable="false" sap:filterable="false" sap:semantics="unit-of-measure"/>
                <Property Name="Netwr" Type="Edm.Decimal" Nullable="false" Precision="16" Scale="3" sap:unit="Waers" sap:label="Net değer" sap:creatable="false" sap:updatable="false" sap:sortable="false" sap:filterable="false"/>
                <Property Name="Waers" Type="Edm.String" Nullable="false" MaxLength="5" sap:label="Para birimi" sap:creatable="false" sap:updatable="false" sap:sortable="false" sap:filterable="false" sap:semantics="currency-code"/>
                <Property Name="NetwrT" Type="Edm.Decimal" Nullable="false" Precision="16" Scale="3" sap:unit="Waers" sap:label="Net değer" sap:creatable="false" sap:updatable="false" sap:sortable="false" sap:filterable="false"/>
                <Property Name="Name1" Type="Edm.String" Nullable="false" MaxLength="30" sap:label="Ad 1" sap:creatable="false" sap:updatable="false" sap:sortable="false" sap:filterable="false"/>
            </EntityType>
            <EntityType Name="EData" sap:content-version="1">
                <Key>
                    <PropertyRef Name="Matnr"/>
                    <PropertyRef Name="Werks"/>
                    <PropertyRef Name="Lgort"/>
                    <PropertyRef Name="Charg"/>
                    <PropertyRef Name="Sobkz"/>
                    <PropertyRef Name="Vbeln"/>
                    <PropertyRef Name="Posnr"/>
                </Key>
                <Property Name="Matnr" Type="Edm.String" Nullable="false" MaxLength="18" sap:label="Malzeme" sap:creatable="false" sap:updatable="false" sap:sortable="false" sap:filterable="false"/>
                <Property Name="Werks" Type="Edm.String" Nullable="false" MaxLength="4" sap:label="Üretim yeri" sap:creatable="false" sap:updatable="false" sap:sortable="false" sap:filterable="false"/>
                <Property Name="Lgort" Type="Edm.String" Nullable="false" MaxLength="4" sap:label="Depo yeri" sap:creatable="false" sap:updatable="false" sap:sortable="false" sap:filterable="false"/>
                <Property Name="Charg" Type="Edm.String" Nullable="false" MaxLength="10" sap:label="Parti" sap:creatable="false" sap:updatable="false" sap:sortable="false" sap:filterable="false"/>
                <Property Name="Sobkz" Type="Edm.String" Nullable="false" MaxLength="1" sap:label="Özel stok" sap:creatable="false" sap:updatable="false" sap:sortable="false" sap:filterable="false"/>
                <Property Name="Vbeln" Type="Edm.String" Nullable="false" MaxLength="10" sap:label="SD belgesi" sap:creatable="false" sap:updatable="false" sap:sortable="false" sap:filterable="false"/>
                <Property Name="Posnr" Type="Edm.String" Nullable="false" MaxLength="6" sap:label="Kalem" sap:creatable="false" sap:updatable="false" sap:sortable="false" sap:filterable="false"/>
                <Property Name="Kalab" Type="Edm.Decimal" Nullable="false" Precision="13" Scale="3" sap:label="Tahditsiz klnb." sap:creatable="false" sap:updatable="false" sap:sortable="false" sap:filterable="false"/>
                <Property Name="Kains" Type="Edm.Decimal" Nullable="false" Precision="13" Scale="3" sap:label="Klt.kontrolünde" sap:creatable="false" sap:updatable="false" sap:sortable="false" sap:filterable="false"/>
                <Property Name="Kaspe" Type="Edm.Decimal" Nullable="false" Precision="13" Scale="3" sap:label="Bloke" sap:creatable="false" sap:updatable="false" sap:sortable="false" sap:filterable="false"/>
                <Property Name="Toplam" Type="Edm.Decimal" Nullable="false" Precision="13" Scale="3" sap:label="Tahditsiz klnb." sap:creatable="false" sap:updatable="false" sap:sortable="false" sap:filterable="false"/>
                <Property Name="Name1" Type="Edm.String" Nullable="false" MaxLength="30" sap:label="Ad 1" sap:creatable="false" sap:updatable="false" sap:sortable="false" sap:filterable="false"/>
                <Property Name="Netwr" Type="Edm.Decimal" Nullable="false" Precision="16" Scale="3" sap:label="Net değer" sap:creatable="false" sap:updatable="false" sap:sortable="false" sap:filterable="false"/>
                <Property Name="Waerk" Type="Edm.String" Nullable="false" MaxLength="5" sap:label="Belge PB" sap:creatable="false" sap:updatable="false" sap:sortable="false" sap:filterable="false" sap:semantics="currency-code"/>
                <Property Name="Vkorg" Type="Edm.String" Nullable="false" MaxLength="4" sap:label="Satış org." sap:creatable="false" sap:updatable="false" sap:sortable="false" sap:filterable="false"/>
                <Property Name="Vtweg" Type="Edm.String" Nullable="false" MaxLength="2" sap:label="Dağıtım kanalı" sap:creatable="false" sap:updatable="false" sap:sortable="false" sap:filterable="false"/>
                <Property Name="Spart" Type="Edm.String" Nullable="false" MaxLength="2" sap:label="Bölüm" sap:creatable="false" sap:updatable="false" sap:sortable="false" sap:filterable="false"/>
                <Property Name="Vkgrp" Type="Edm.String" Nullable="false" MaxLength="3" sap:label="Satış grubu" sap:creatable="false" sap:updatable="false" sap:sortable="false" sap:filterable="false"/>
                <Property Name="Vkbur" Type="Edm.String" Nullable="false" MaxLength="4" sap:label="Satış bürosu" sap:creatable="false" sap:updatable="false" sap:sortable="false" sap:filterable="false"/>
                <Property Name="Kunnr" Type="Edm.String" Nullable="false" MaxLength="10" sap:label="Sipariş veren" sap:creatable="false" sap:updatable="false" sap:sortable="false" sap:filterable="false"/>
            </EntityType>
            <EntityType Name="EtZmm" sap:content-version="1">
                <Key>
                    <PropertyRef Name="Matnr"/>
                    <PropertyRef Name="Werks"/>
                    <PropertyRef Name="Lgort"/>
                    <PropertyRef Name="Charg"/>
                    <PropertyRef Name="Sobkz"/>
                    <PropertyRef Name="Vbeln"/>
                    <PropertyRef Name="Posnr"/>
                </Key>
                <Property Name="Matnr" Type="Edm.String" Nullable="false" MaxLength="18" sap:label="Malzeme" sap:creatable="false" sap:updatable="false" sap:sortable="false" sap:filterable="false"/>
                <Property Name="Werks" Type="Edm.String" Nullable="false" MaxLength="4" sap:label="Üretim yeri" sap:creatable="false" sap:updatable="false" sap:sortable="false" sap:filterable="false"/>
                <Property Name="Lgort" Type="Edm.String" Nullable="false" MaxLength="4" sap:label="Depo yeri" sap:creatable="false" sap:updatable="false" sap:sortable="false" sap:filterable="false"/>
                <Property Name="Charg" Type="Edm.String" Nullable="false" MaxLength="10" sap:label="Parti" sap:creatable="false" sap:updatable="false" sap:sortable="false" sap:filterable="false"/>
                <Property Name="Sobkz" Type="Edm.String" Nullable="false" MaxLength="1" sap:label="Özel stok" sap:creatable="false" sap:updatable="false" sap:sortable="false" sap:filterable="false"/>
                <Property Name="Vbeln" Type="Edm.String" Nullable="false" MaxLength="10" sap:label="SD belgesi" sap:creatable="false" sap:updatable="false" sap:sortable="false" sap:filterable="false"/>
                <Property Name="Posnr" Type="Edm.String" Nullable="false" MaxLength="6" sap:label="Kalem" sap:creatable="false" sap:updatable="false" sap:sortable="false" sap:filterable="false"/>
                <Property Name="Kalab" Type="Edm.Decimal" Nullable="false" Precision="13" Scale="3" sap:label="Tahditsiz klnb." sap:creatable="false" sap:updatable="false" sap:sortable="false" sap:filterable="false"/>
                <Property Name="Kains" Type="Edm.Decimal" Nullable="false" Precision="13" Scale="3" sap:label="Klt.kontrolünde" sap:creatable="false" sap:updatable="false" sap:sortable="false" sap:filterable="false"/>
                <Property Name="Kaspe" Type="Edm.Decimal" Nullable="false" Precision="13" Scale="3" sap:label="Bloke" sap:creatable="false" sap:updatable="false" sap:sortable="false" sap:filterable="false"/>
                <Property Name="Toplam" Type="Edm.Decimal" Nullable="false" Precision="13" Scale="3" sap:label="Tahditsiz klnb." sap:creatable="false" sap:updatable="false" sap:sortable="false" sap:filterable="false"/>
                <Property Name="Name1" Type="Edm.String" Nullable="false" MaxLength="30" sap:label="Ad 1" sap:creatable="false" sap:updatable="false" sap:sortable="false" sap:filterable="false"/>
                <Property Name="Netwr" Type="Edm.Decimal" Nullable="false" Precision="17" Scale="3" sap:label="Net değer" sap:creatable="false" sap:updatable="false" sap:sortable="false" sap:filterable="false"/>
                <Property Name="Waerk" Type="Edm.String" Nullable="false" MaxLength="5" sap:label="Belge PB" sap:creatable="false" sap:updatable="false" sap:sortable="false" sap:filterable="false"/>
                <Property Name="Vkorg" Type="Edm.String" Nullable="false" MaxLength="4" sap:label="Satış org." sap:creatable="false" sap:updatable="false" sap:sortable="false" sap:filterable="false"/>
                <Property Name="Vtweg" Type="Edm.String" Nullable="false" MaxLength="2" sap:label="Dağıtım kanalı" sap:creatable="false" sap:updatable="false" sap:sortable="false" sap:filterable="false"/>
                <Property Name="Spart" Type="Edm.String" Nullable="false" MaxLength="2" sap:label="Bölüm" sap:creatable="false" sap:updatable="false" sap:sortable="false" sap:filterable="false"/>
                <Property Name="Vkgrp" Type="Edm.String" Nullable="false" MaxLength="3" sap:label="Satış grubu" sap:creatable="false" sap:updatable="false" sap:sortable="false" sap:filterable="false"/>
                <Property Name="Vkbur" Type="Edm.String" Nullable="false" MaxLength="4" sap:label="Satış bürosu" sap:creatable="false" sap:updatable="false" sap:sortable="false" sap:filterable="false"/>
                <Property Name="Kunnr" Type="Edm.String" Nullable="false" MaxLength="10" sap:label="Sipariş veren" sap:creatable="false" sap:updatable="false" sap:sortable="false" sap:filterable="false"/>
            </EntityType>
            <EntityContainer Name="ZFIORI_EGITIM_SRV_Entities" m:IsDefaultEntityContainer="true" sap:supported-formats="atom json xlsx">
                <EntitySet Name="EUrunlerSet" EntityType="ZFIORI_EGITIM_SRV.EUrunler" sap:creatable="false" sap:updatable="false" sap:deletable="false" sap:pageable="false" sap:content-version="1"/>
                <EntitySet Name="EKarakteristikSet" EntityType="ZFIORI_EGITIM_SRV.EKarakteristik" sap:creatable="false" sap:updatable="false" sap:deletable="false" sap:pageable="false" sap:content-version="1"/>
                <EntitySet Name="MalzFiyatSet" EntityType="ZFIORI_EGITIM_SRV.MalzFiyat" sap:creatable="false" sap:updatable="false" sap:deletable="false" sap:pageable="false" sap:content-version="1"/>
                <EntitySet Name="FiyatSet" EntityType="ZFIORI_EGITIM_SRV.Fiyat" sap:creatable="false" sap:updatable="false" sap:deletable="false" sap:pageable="false" sap:content-version="1"/>
                <EntitySet Name="KayitDenemeSet" EntityType="ZFIORI_EGITIM_SRV.KayitDeneme" sap:creatable="false" sap:updatable="false" sap:deletable="false" sap:pageable="false" sap:addressable="false" sap:content-version="1"/>
                <EntitySet Name="VendorSet" EntityType="ZFIORI_EGITIM_SRV.Vendor" sap:creatable="false" sap:updatable="false" sap:deletable="false" sap:pageable="false" sap:content-version="1"/>
                <EntitySet Name="SirketSet" EntityType="ZFIORI_EGITIM_SRV.Sirket" sap:creatable="false" sap:updatable="false" sap:deletable="false" sap:pageable="false" sap:content-version="1"/>
                <EntitySet Name="MipSet" EntityType="ZFIORI_EGITIM_SRV.Mip" sap:creatable="false" sap:updatable="false" sap:deletable="false" sap:pageable="false" sap:content-version="1"/>
                <EntitySet Name="MusteriSet" EntityType="ZFIORI_EGITIM_SRV.Musteri" sap:creatable="false" sap:updatable="false" sap:deletable="false" sap:pageable="false" sap:content-version="1"/>
                <EntitySet Name="NakitListSet" EntityType="ZFIORI_EGITIM_SRV.NakitList" sap:creatable="false" sap:updatable="false" sap:deletable="false" sap:pageable="false" sap:content-version="1"/>
                <EntitySet Name="EDepoSet" EntityType="ZFIORI_EGITIM_SRV.EDepo" sap:creatable="false" sap:updatable="false" sap:deletable="false" sap:pageable="false" sap:content-version="1"/>
                <EntitySet Name="EData001Set" EntityType="ZFIORI_EGITIM_SRV.EData" sap:creatable="false" sap:updatable="false" sap:deletable="false" sap:pageable="false" sap:content-version="1"/>
                <EntitySet Name="EtZmmSet" EntityType="ZFIORI_EGITIM_SRV.EtZmm" sap:creatable="false" sap:updatable="false" sap:deletable="false" sap:pageable="false" sap:content-version="1"/>
            </EntityContainer>
            <atom:link rel="self" href="http://10.238.2.23:8000/sap/opu/odata/sap/ZFIORI_EGITIM_SRV/$metadata" xmlns:atom="http://www.w3.org/2005/Atom"/>
            <atom:link rel="latest-version" href="http://10.238.2.23:8000/sap/opu/odata/sap/ZFIORI_EGITIM_SRV/$metadata" xmlns:atom="http://www.w3.org/2005/Atom"/>
        </Schema>
    </edmx:DataServices>
</edmx:Edmx>